{
  "type": "Item",
  "folder": "lr85fBx5XwieZOfH",
  "name": "Chimera Malice",
  "color": null,
  "sorting": "a",
  "_id": "nei486z2dWBGSLAG",
  "description": "",
  "sort": 0,
  "flags": {},
  "_stats": {
    "compendiumSource": null,
    "duplicateSource": null,
    "exportSource": null,
    "coreVersion": "13.348",
    "systemId": "draw-steel",
    "systemVersion": "0.8.1",
    "createdTime": 1757096257519,
    "modifiedTime": null,
    "lastModifiedBy": null
  },
  "_key": "!folders!nei486z2dWBGSLAG"
}
