{
  "name": "Spiny Turtle",
  "type": "treasure",
  "img": "icons/equipment/chest/breastplate-gorget-steel.webp",
  "folder": "5RZq8kMsUYHbLjTy",
  "effects": [],
  "flags": {},
  "system": {
    "description": {
      "value": "<p><em>This heavy mechanized plate armor of gnomish make is designed to create its own cover on the battlefield.</em></p><p><strong>1st Level:</strong> While you wear this armor, you gain a +6 bonus to Stamina. Additionally, you can use a main action to expand the armor on your back to create a 4 wall of metal behind you. The wall is an object that retracts if you move, or if it takes [[/damage 15]] damage. It then requires a main action to recalibrate before it can be deployed again.</p><p><strong>5th Level:</strong> The armor’s bonus to Stamina increases to +12, and the damage the wall can take before retracting increases to 25. Additionally, while the wall is expanded, spikes extrude from it, and any creature who deals damage to the wall while adjacent to it takes [[/damage 3]] damage.</p><p><strong>9th Level:</strong> The armor’s bonus to Stamina increases to +21. Additionally, spikes cover the armor, and any adjacent creature who deals damage to you takes [[/damage 6]] damage.</p>",
      "director": ""
    },
    "source": {
      "book": "Heroes",
      "page": "329",
      "license": "Draw Steel Creator License"
    },
    "_dsid": "treasure",
    "kind": "armor",
    "category": "leveled",
    "echelon": 1,
    "keywords": [
      "magic",
      "heavy"
    ],
    "quantity": 1,
    "project": {
      "prerequisites": "Ten steel gears from an ancient construct",
      "source": "Texts or lore in Variac",
      "rollCharacteristic": [
        "might",
        "reason",
        "intuition"
      ],
      "yield": {
        "amount": "1",
        "display": ""
      },
      "goal": 450
    }
  },
  "ownership": {
    "default": 0
  },
  "_stats": {
    "compendiumSource": null,
    "duplicateSource": null,
    "exportSource": null,
    "coreVersion": "13.351",
    "systemId": "draw-steel",
    "systemVersion": "0.9.0",
    "createdTime": 1763209724753,
    "modifiedTime": null,
    "lastModifiedBy": null
  },
  "_id": "CFbgEXJ5ptQUuILJ",
  "sort": 300000,
  "_key": "!items!CFbgEXJ5ptQUuILJ"
}
