{
  "name": "Panther",
  "type": "kit",
  "_id": "jHJnlHyRRNf9V5hm",
  "img": "icons/weapons/hammers/hammer-double-engraved-ruby.webp",
  "system": {
    "description": {
      "value": "<p>If you want a good balance of protection, speed, and damage, the Panther kit is for you. This kit increases your Stamina not by wearing armor, but through the focused battle preparation of body and mind, letting you be fast and mobile while swinging a heavy weapon at your foes</p>",
      "director": ""
    },
    "source": {
      "book": "Heroes",
      "page": "221",
      "license": "Draw Steel Creator License",
      "revision": 1
    },
    "_dsid": "panther",
    "advancements": {
      "iCOS98pyguCqGwty": {
        "name": "Devastating Rush",
        "img": null,
        "type": "itemGrant",
        "requirements": {
          "level": null
        },
        "_id": "iCOS98pyguCqGwty",
        "pool": [
          {
            "uuid": "Compendium.draw-steel.abilities.Item.qenjWplO46ZaPjdb"
          }
        ]
      }
    },
    "equipment": {
      "armor": "none",
      "weapon": [
        "heavy"
      ],
      "shield": false
    },
    "bonuses": {
      "melee": {
        "damage": {
          "tier1": 0,
          "tier2": 0,
          "tier3": 4
        },
        "distance": null
      },
      "ranged": {
        "damage": {
          "tier1": 0,
          "tier2": 0,
          "tier3": 0
        },
        "distance": null
      },
      "stamina": 6,
      "speed": 1,
      "stability": 1,
      "disengage": null
    }
  },
  "effects": [],
  "folder": null,
  "sort": 0,
  "ownership": {
    "default": 0,
    "kZoV8xj0DBrnj5EN": 3
  },
  "flags": {},
  "_stats": {
    "compendiumSource": null,
    "duplicateSource": null,
    "exportSource": null,
    "coreVersion": "13.346",
    "systemId": "draw-steel",
    "systemVersion": "0.8.0",
    "createdTime": 1754362179505,
    "modifiedTime": null,
    "lastModifiedBy": null
  },
  "_key": "!items!jHJnlHyRRNf9V5hm"
}
