{
  "name": "Conditions",
  "_id": "hDhdILCi65wpBgPZ",
  "pages": [
    {
      "sort": 0,
      "name": "Conditions",
      "type": "text",
      "_id": "1TJwpxf7ykd0HBEu",
      "system": {},
      "title": {
        "show": true,
        "level": 1
      },
      "image": {},
      "text": {
        "format": 1,
        "content": "<p>Some abilities and other effects apply specific negative effects called conditions to a creature. The following conditions show up regularly in the game and can be tracked on your character sheet.</p>"
      },
      "video": {
        "controls": true,
        "volume": 0.5
      },
      "src": null,
      "ownership": {
        "default": -1
      },
      "flags": {},
      "_stats": {
        "compendiumSource": null,
        "duplicateSource": null,
        "coreVersion": "13.339",
        "systemId": "draw-steel",
        "systemVersion": "0.1.0",
        "createdTime": null,
        "modifiedTime": 1735075844036,
        "lastModifiedBy": "cpRCYfteS3IEfu8O",
        "exportSource": null
      },
      "category": null,
      "_key": "!journal.pages!hDhdILCi65wpBgPZ.1TJwpxf7ykd0HBEu"
    },
    {
      "sort": 100000,
      "name": "Bleeding",
      "type": "text",
      "_id": "YzgERGFhFphgpjKQ",
      "system": {},
      "title": {
        "show": true,
        "level": 2
      },
      "image": {},
      "text": {
        "format": 1,
        "content": "<p>While bleeding, whenever you make a test using Might or Agility, make a strike, or use an action, maneuver, or a triggered action, you lose 1d6 Stamina after the test, action, maneuver, or triggered action is resolved. This Stamina loss can’t be prevented in any way.</p>"
      },
      "video": {
        "controls": true,
        "volume": 0.5
      },
      "src": null,
      "ownership": {
        "default": -1
      },
      "flags": {},
      "_stats": {
        "compendiumSource": null,
        "duplicateSource": null,
        "coreVersion": "13.339",
        "systemId": "draw-steel",
        "systemVersion": "0.1.0",
        "createdTime": null,
        "modifiedTime": 1735075816104,
        "lastModifiedBy": "cpRCYfteS3IEfu8O",
        "exportSource": null
      },
      "category": null,
      "_key": "!journal.pages!hDhdILCi65wpBgPZ.YzgERGFhFphgpjKQ"
    },
    {
      "sort": 200000,
      "name": "Dazed",
      "type": "text",
      "_id": "K2dZpCsAOU7xMpWb",
      "system": {},
      "title": {
        "show": true,
        "level": 2
      },
      "image": {},
      "text": {
        "format": 1,
        "content": "<p>While you are dazed, you can do only one thing on your turn: use a maneuver, use an action, or take a move action. You also can’t use triggered actions, free triggered actions, or free maneuvers.</p>"
      },
      "video": {
        "controls": true,
        "volume": 0.5
      },
      "src": null,
      "ownership": {
        "default": -1
      },
      "flags": {},
      "_stats": {
        "compendiumSource": null,
        "duplicateSource": null,
        "coreVersion": "13.339",
        "systemId": "draw-steel",
        "systemVersion": "0.1.0",
        "createdTime": null,
        "modifiedTime": 1735075829583,
        "lastModifiedBy": "cpRCYfteS3IEfu8O",
        "exportSource": null
      },
      "category": null,
      "_key": "!journal.pages!hDhdILCi65wpBgPZ.K2dZpCsAOU7xMpWb"
    },
    {
      "sort": 300000,
      "name": "Frightened",
      "type": "text",
      "_id": "bXiI9vUF3tF78qXg",
      "system": {},
      "title": {
        "show": true,
        "level": 2
      },
      "image": {},
      "text": {
        "format": 1,
        "content": "<p>If you are frightened, ability power rolls you make against the source of your fear take a bane. If that source is a creature, their ability power rolls against you gain an edge. You can’t willingly move closer to the source of your fear if you know the location of that source. If you gain the frightened condition from one source while already frightened by a different source, the new condition replaces the old one.</p>"
      },
      "video": {
        "controls": true,
        "volume": 0.5
      },
      "src": null,
      "ownership": {
        "default": -1
      },
      "flags": {},
      "_stats": {
        "compendiumSource": null,
        "duplicateSource": null,
        "coreVersion": "13.339",
        "systemId": "draw-steel",
        "systemVersion": "0.1.0",
        "createdTime": null,
        "modifiedTime": 1735075864628,
        "lastModifiedBy": "cpRCYfteS3IEfu8O",
        "exportSource": null
      },
      "category": null,
      "_key": "!journal.pages!hDhdILCi65wpBgPZ.bXiI9vUF3tF78qXg"
    },
    {
      "sort": 400000,
      "name": "Grabbed",
      "type": "text",
      "_id": "aWBP2vfXXM3fzuVn",
      "system": {},
      "title": {
        "show": true,
        "level": 2
      },
      "image": {},
      "text": {
        "format": 1,
        "content": "<p>While you are grabbed, your speed is 0, you can’t be force moved, you can’t use the Knockback maneuver, and you take a bane on abilities that don’t target the creature grabbing you. If the creature grabbing you moves, they bring you with them. If the creature’s size is equal to or less than yours, their speed is halved while they have you grabbed.</p><p> The creature grabbing you can use a maneuver to move you into an unoccupied space adjacent to them. </p><p>The creature grabbing you can end the grab at any time (no action required). You can also attempt to escape being grabbed using the Escape Grab maneuver (see Maneuvers in Combat). If you teleport or if the creature grabbing you is force moved to a space that isn’t adjacent to you, you are no longer grabbed.</p>"
      },
      "video": {
        "controls": true,
        "volume": 0.5
      },
      "src": null,
      "ownership": {
        "default": -1
      },
      "flags": {},
      "_stats": {
        "compendiumSource": null,
        "duplicateSource": null,
        "coreVersion": "13.339",
        "systemId": "draw-steel",
        "systemVersion": "0.1.0",
        "createdTime": null,
        "modifiedTime": 1735075893535,
        "lastModifiedBy": "cpRCYfteS3IEfu8O",
        "exportSource": null
      },
      "category": null,
      "_key": "!journal.pages!hDhdILCi65wpBgPZ.aWBP2vfXXM3fzuVn"
    },
    {
      "sort": 500000,
      "name": "Prone",
      "type": "text",
      "_id": "v11clsSMgoFZm3V8",
      "system": {},
      "title": {
        "show": true,
        "level": 2
      },
      "image": {},
      "text": {
        "format": 1,
        "content": "<p>While you are prone, you are flat on the ground, strikes you make take a bane, and melee abilities made against you gain an edge. You must crawl to move along the ground, which costs you 1 additional square of movement for every square you crawl. You can’t climb, jump, swim, or fly while prone. If you are climbing, flying, or jumping while you are knocked prone, you fall. </p><p>While prone, you can stand up as a maneuver (see Maneuvers in Combat), unless the ability or effect that imposed the condition says otherwise. You can use a maneuver to make an adjacent prone creature stand up.</p>"
      },
      "video": {
        "controls": true,
        "volume": 0.5
      },
      "src": null,
      "ownership": {
        "default": -1
      },
      "flags": {},
      "_stats": {
        "compendiumSource": null,
        "duplicateSource": null,
        "coreVersion": "13.339",
        "systemId": "draw-steel",
        "systemVersion": "0.1.0",
        "createdTime": null,
        "modifiedTime": 1735075910505,
        "lastModifiedBy": "cpRCYfteS3IEfu8O",
        "exportSource": null
      },
      "category": null,
      "_key": "!journal.pages!hDhdILCi65wpBgPZ.v11clsSMgoFZm3V8"
    },
    {
      "sort": 600000,
      "name": "Restrained",
      "type": "text",
      "_id": "6IfH6beu8LjK08Oj",
      "system": {},
      "title": {
        "show": true,
        "level": 2
      },
      "image": {},
      "text": {
        "format": 1,
        "content": "<p>While you are restrained, your speed is 0, you can’t use the Stand Up maneuver, and you can’t be force moved. Your ability power rolls take a bane, abilities against you gain an edge, and you have a bane on Might and Agility tests. </p><p>If you teleport while restrained, the condition ends.</p>"
      },
      "video": {
        "controls": true,
        "volume": 0.5
      },
      "src": null,
      "ownership": {
        "default": -1
      },
      "flags": {},
      "_stats": {
        "compendiumSource": null,
        "duplicateSource": null,
        "coreVersion": "13.339",
        "systemId": "draw-steel",
        "systemVersion": "0.1.0",
        "createdTime": null,
        "modifiedTime": 1735075928328,
        "lastModifiedBy": "cpRCYfteS3IEfu8O",
        "exportSource": null
      },
      "category": null,
      "_key": "!journal.pages!hDhdILCi65wpBgPZ.6IfH6beu8LjK08Oj"
    },
    {
      "sort": 700000,
      "name": "Slowed",
      "type": "text",
      "_id": "aFEwQG4OcYDNp8DL",
      "system": {},
      "title": {
        "show": true,
        "level": 2
      },
      "image": {},
      "text": {
        "format": 1,
        "content": "<p>While you are slowed, your speed is 2 unless it is already lower, and you can’t shift.</p>"
      },
      "video": {
        "controls": true,
        "volume": 0.5
      },
      "src": null,
      "ownership": {
        "default": -1
      },
      "flags": {},
      "_stats": {
        "compendiumSource": null,
        "duplicateSource": null,
        "coreVersion": "13.339",
        "systemId": "draw-steel",
        "systemVersion": "0.1.0",
        "createdTime": null,
        "modifiedTime": 1735075939637,
        "lastModifiedBy": "cpRCYfteS3IEfu8O",
        "exportSource": null
      },
      "category": null,
      "_key": "!journal.pages!hDhdILCi65wpBgPZ.aFEwQG4OcYDNp8DL"
    },
    {
      "sort": 800000,
      "name": "Taunted",
      "type": "text",
      "_id": "9zseFmXdcSw8MuKh",
      "system": {},
      "title": {
        "show": true,
        "level": 2
      },
      "image": {},
      "text": {
        "format": 1,
        "content": "<p>If you are taunted, you have a double bane on ability power rolls that don’t target the creature who taunted you while you have line of effect to that creature. If you gain the taunted condition from one creature while already taunted by a different creature, the new condition replaces the old one.</p>"
      },
      "video": {
        "controls": true,
        "volume": 0.5
      },
      "src": null,
      "ownership": {
        "default": -1
      },
      "flags": {},
      "_stats": {
        "compendiumSource": null,
        "duplicateSource": null,
        "coreVersion": "13.339",
        "systemId": "draw-steel",
        "systemVersion": "0.1.0",
        "createdTime": null,
        "modifiedTime": 1735075952628,
        "lastModifiedBy": "cpRCYfteS3IEfu8O",
        "exportSource": null
      },
      "category": null,
      "_key": "!journal.pages!hDhdILCi65wpBgPZ.9zseFmXdcSw8MuKh"
    },
    {
      "sort": 900000,
      "name": "Weakened",
      "type": "text",
      "_id": "QZpLhRT6imKlqZ1n",
      "system": {},
      "title": {
        "show": true,
        "level": 2
      },
      "image": {},
      "text": {
        "format": 1,
        "content": "<p>While you are weakened, all your power rolls take a bane.</p>"
      },
      "video": {
        "controls": true,
        "volume": 0.5
      },
      "src": null,
      "ownership": {
        "default": -1
      },
      "flags": {},
      "_stats": {
        "compendiumSource": null,
        "duplicateSource": null,
        "coreVersion": "13.339",
        "systemId": "draw-steel",
        "systemVersion": "0.1.0",
        "createdTime": null,
        "modifiedTime": 1735075964299,
        "lastModifiedBy": "cpRCYfteS3IEfu8O",
        "exportSource": null
      },
      "category": null,
      "_key": "!journal.pages!hDhdILCi65wpBgPZ.QZpLhRT6imKlqZ1n"
    }
  ],
  "folder": "wnqp2PFeCN9C0VOw",
  "flags": {},
  "_stats": {
    "compendiumSource": null,
    "duplicateSource": null,
    "coreVersion": "13.339",
    "systemId": "draw-steel",
    "systemVersion": "0.1.0",
    "createdTime": 1728311383486,
    "modifiedTime": 1728311402674,
    "lastModifiedBy": "bGEAks7GRFILpzQz",
    "exportSource": null
  },
  "sort": 100000,
  "ownership": {
    "default": 0,
    "bGEAks7GRFILpzQz": 3
  },
  "categories": [],
  "_key": "!journal!hDhdILCi65wpBgPZ"
}
