{
  "folder": "rdU05mKMnnKBRTnA",
  "name": "Eidetic Memory",
  "type": "feature",
  "img": "icons/commodities/biological/organ-brain-pink-purple.webp",
  "system": {
    "description": {
      "value": "<p>Your mind is an encyclopedia, though not always an easy one to organize. When you finish a respite, choose one skill from the lore skill group that you don’t have. You have that skill until you finish your next respite. Additionally, if you spend 1 uninterrupted minute or more reading any page of text, you can memorize its contents, allowing you to memorize entire books with sufficient time.</p>",
      "director": ""
    },
    "source": {
      "book": "Heroes",
      "page": "230",
      "license": "Draw Steel Creator License",
      "revision": 1
    },
    "_dsid": "area-of-expertise",
    "advancements": {},
    "type": {
      "value": "perk",
      "subtype": "lore"
    },
    "prerequisites": {
      "value": ""
    }
  },
  "effects": [],
  "ownership": {
    "default": 0,
    "whGCKogBJnD2ehjg": 3
  },
  "flags": {},
  "_stats": {
    "compendiumSource": null,
    "duplicateSource": null,
    "exportSource": null,
    "coreVersion": "13.346",
    "systemId": "draw-steel",
    "systemVersion": "0.8.0",
    "createdTime": 1754513289356,
    "modifiedTime": null,
    "lastModifiedBy": null
  },
  "_id": "OhV61irKCVuHZaAk",
  "sort": 0,
  "_key": "!items!OhV61irKCVuHZaAk"
}
