{
  "folder": "RIJxpeIvIwDbhF0P",
  "name": "Acolyte of Earth",
  "type": "feature",
  "_id": "qKvNIOUQmZohk43r",
  "img": "icons/magic/earth/construct-stone-long-arms.webp",
  "system": {
    "description": {
      "value": "<p>You harness the flow of earth magic to become harder to move. Whenever you use an ability that has the Earth and Magic keywords, your stability increases by 1 until the start of your next turn. This benefit is cumulative.</p>",
      "director": ""
    },
    "source": {
      "book": "Heroes",
      "page": "113",
      "license": "Draw Steel Creator License",
      "revision": 1
    },
    "_dsid": "acolyte-of-earth",
    "advancements": {}
  },
  "effects": [],
  "sort": 100000,
  "ownership": {
    "default": 0
  },
  "flags": {},
  "_stats": {
    "compendiumSource": null,
    "duplicateSource": null,
    "exportSource": null,
    "coreVersion": "13.347",
    "systemId": "draw-steel",
    "systemVersion": "0.8.0",
    "createdTime": 1755712366363,
    "modifiedTime": null,
    "lastModifiedBy": null
  },
  "_key": "!items!qKvNIOUQmZohk43r"
}
