{
  "folder": "MSkFVitLtUZwMJIQ",
  "name": "Blade of the Heavens",
  "type": "ability",
  "_id": "YHCqOWlqzXPL34zs",
  "img": "icons/weapons/swords/sword-winged-pink.webp",
  "system": {
    "source": {
      "book": "Heroes",
      "page": "106",
      "license": "Draw Steel Creator License"
    },
    "_dsid": "blade-of-the-heavens",
    "story": "A greatsword streams down from the sky, threatening to pin your foe.",
    "keywords": [
      "magic",
      "ranged",
      "strike"
    ],
    "type": "main",
    "category": "heroic",
    "resource": 9,
    "trigger": "",
    "distance": {
      "type": "ranged",
      "primary": 5
    },
    "damageDisplay": "melee",
    "target": {
      "type": "creature",
      "custom": "",
      "value": 1
    },
    "power": {
      "roll": {
        "formula": "@chr",
        "characteristics": [
          "intuition"
        ]
      },
      "effects": {
        "kOhxN0zgpT5TnPeT": {
          "name": "",
          "img": null,
          "type": "damage",
          "_id": "kOhxN0zgpT5TnPeT",
          "damage": {
            "tier1": {
              "value": "8 + @chr"
            },
            "tier2": {
              "value": "12 + @chr"
            },
            "tier3": {
              "value": "16 + @chr"
            }
          }
        },
        "eqnQeNzsNwjOcZ4N": {
          "name": "",
          "img": null,
          "type": "applied",
          "_id": "eqnQeNzsNwjOcZ4N",
          "applied": {
            "tier1": {
              "display": "{{potency}}, prone and restrained (save ends)",
              "potency": {
                "characteristic": "agility"
              },
              "effects": {
                "prone": {
                  "condition": "failure",
                  "end": ""
                },
                "restrained": {
                  "condition": "failure",
                  "end": "save"
                }
              }
            },
            "tier2": {
              "effects": {
                "prone": {
                  "condition": "failure",
                  "end": ""
                },
                "restrained": {
                  "condition": "failure",
                  "end": "save"
                }
              }
            },
            "tier3": {
              "effects": {
                "prone": {
                  "condition": "failure",
                  "end": ""
                },
                "restrained": {
                  "condition": "failure",
                  "end": "save"
                }
              }
            }
          }
        }
      }
    },
    "effect": {
      "before": "",
      "after": ""
    },
    "spend": {
      "text": "",
      "value": null
    },
    "prerequisites": {
      "dsid": [
        "war"
      ]
    }
  },
  "effects": [],
  "sort": 100000,
  "ownership": {
    "default": 0
  },
  "flags": {},
  "_stats": {
    "compendiumSource": null,
    "duplicateSource": null,
    "exportSource": null,
    "coreVersion": "13.351",
    "systemId": "draw-steel",
    "systemVersion": "0.10.0",
    "createdTime": 1760753730354,
    "modifiedTime": null,
    "lastModifiedBy": null
  },
  "_key": "!items!YHCqOWlqzXPL34zs"
}
