{
  "folder": "0Wss47OeUBckZUjf",
  "name": "Immoveable Object",
  "type": "feature",
  "_id": "r9MvlUYI9RRrCApy",
  "img": "icons/magic/defensive/shield-barrier-glowing-blue.webp",
  "system": {
    "description": {
      "value": "<p>You add your level to your effective size for the purpose of interacting with creatures and objects, including determining whether you can lift an object, are affected by forced movement, and so forth. This has no effect on whether you can be grabbed.</p><p>Additionally, you have a bonus to stability equal to your Might score.</p>",
      "director": ""
    },
    "source": {
      "book": "Heroes",
      "page": "136",
      "license": "Draw Steel Creator License"
    },
    "_dsid": "immoveable-object",
    "advancements": {}
  },
  "effects": [
    {
      "name": "Immovable Object Effect",
      "img": "icons/magic/defensive/shield-barrier-glowing-blue.webp",
      "type": "base",
      "origin": "Compendium.draw-steel.classes.Item.r9MvlUYI9RRrCApy",
      "_id": "PrLyqZ4hQtYFOTxP",
      "system": {
        "end": {
          "type": "",
          "roll": "1d10 + @combat.save.bonus"
        }
      },
      "changes": [
        {
          "key": "system.combat.stability",
          "mode": 2,
          "value": "2",
          "priority": null
        }
      ],
      "disabled": false,
      "duration": {
        "startTime": null,
        "combat": null,
        "seconds": null,
        "rounds": null,
        "turns": null,
        "startRound": null,
        "startTurn": null
      },
      "description": "",
      "tint": "#ffffff",
      "transfer": true,
      "statuses": [],
      "sort": 0,
      "flags": {},
      "_stats": {
        "compendiumSource": null,
        "duplicateSource": null,
        "exportSource": null,
        "coreVersion": "13.347",
        "systemId": "draw-steel",
        "systemVersion": "0.8.1",
        "createdTime": 1756685524255,
        "modifiedTime": null,
        "lastModifiedBy": null
      },
      "_key": "!items.effects!r9MvlUYI9RRrCApy.PrLyqZ4hQtYFOTxP"
    }
  ],
  "sort": 0,
  "ownership": {
    "default": 0
  },
  "flags": {},
  "_stats": {
    "compendiumSource": null,
    "duplicateSource": null,
    "exportSource": null,
    "coreVersion": "13.347",
    "systemId": "draw-steel",
    "systemVersion": "0.8.1",
    "createdTime": 1756685203896,
    "modifiedTime": null,
    "lastModifiedBy": null
  },
  "_key": "!items!r9MvlUYI9RRrCApy"
}
